kiosker/__init__.py
kiosker/api.py
kiosker/data.py
kiosker_python_api-1.2.6.dist-info/METADATA
kiosker_python_api-1.2.6.dist-info/WHEEL
kiosker_python_api-1.2.6.dist-info/licenses/LICENSE
kiosker_python_api-1.2.6.dist-info/RECORD
