Metadata-Version: 2.4
Name: kiosker-python-api
Version: 1.2.6
Summary: A python wrapper for the Kiosker API
Project-URL: Homepage, https://kiosker.io
Project-URL: Documentation, https://docs.kiosker.io
Project-URL: Repository, https://github.com/Top-North/kiosker-python.git
Project-URL: Issues, https://github.com/Top-North/kiosker-python/issues
Author-email: Martin Claesson <martin@topnorth.se>
License-Expression: MIT
License-File: LICENSE
Keywords: api,kiosk,kiosker,kiosker pro
Requires-Dist: httpx
Provides-Extra: test
Requires-Dist: pytest; extra == 'test'
